[
  {
    "id": 1,
    "name": "Tipster's Choice",
    "description": "Draw 2 cards from the main deck, keep 1, return the other to the bottom",
    "persistent": false,
    "effect": {
      "type": "draw_and_choose",
      "drawCount": 2,
      "keepCount": 1
    }
  },
  {
    "id": 2,
    "name": "Corner the Market",
    "description": "Take any one face-up market stock for free (not bought: no price move, no ability)",
    "persistent": false,
    "effect": {
      "type": "take_face_up"
    }
  },
  {
    "id": 3,
    "name": "Pump and Dump",
    "description": "Sell 1 stock at double its current price (still a sale: that color falls -1)",
    "persistent": false,
    "effect": {
      "type": "sell_double",
      "count": 1
    }
  },
  {
    "id": 4,
    "name": "The Squeeze",
    "description": "Raise one stock by +2 OR lower one stock by -2",
    "persistent": false,
    "effect": {
      "type": "adjust_stock",
      "amount": 2
    }
  },
  {
    "id": 5,
    "name": "Wild Speculation",
    "description": "Reveal the top main-deck card and put it on the bottom; if it is a colored stock, raise or lower that color by 3 (your choice). If it has no color, reveal again",
    "persistent": false,
    "effect": {
      "type": "flip_and_adjust",
      "amount": 3
    }
  },
  {
    "id": 6,
    "name": "Preferred Bidder",
    "description": "For rest of game, when you tie the winning bid, you win",
    "persistent": true,
    "effect": {
      "type": "tie_breaker"
    }
  },
  {
    "id": 8,
    "name": "Hostile Takeover",
    "description": "Look at another player's hand and take 1 stock of your choice. They receive $6 from the bank",
    "persistent": false,
    "effect": {
      "type": "steal_stock",
      "compensation": 6
    }
  },
  {
    "id": 9,
    "name": "Rumor Mill",
    "description": "Adjust every stock by +1 or -1 (choose per stock)",
    "persistent": false,
    "effect": {
      "type": "adjust_all_stocks",
      "amount": 1
    }
  },
  {
    "id": 10,
    "name": "Inside Track",
    "description": "Look at the top 2 Insider Tip cards and return them in any order",
    "persistent": false,
    "effect": {
      "type": "peek_reorder_tips",
      "count": 2
    }
  },
  {
    "id": 11,
    "name": "Wiretap",
    "description": "Look at the top 2 Insider Tip cards and return them in any order",
    "persistent": false,
    "effect": {
      "type": "peek_reorder_tips",
      "count": 2
    }
  }
]
